Workbook

Sheet Master Summary
A1: TREZO — COMPLETE DEVELOPMENT RECORD
A2: From the first Woven Basket precursor (June 2025) through the live Trezo platform. Good-faith business record; every figure carries its evidence tier.
A4: INPUTS (blue, yellow = edit)
A5: Full-arc start — earliest substantiated precursor (Woven Basket, Nokia credit-collar work) | C5: 45819
A6: Report as of | C6: 46253
A8: THE FULL ARC
A9: Elapsed calendar days | C9: =$C$6-$C$5 -> 434
A10: Inclusive calendar days | C10: =$C$6-$C$5+1 -> 435
A11: Full weeks | C11: =INT(($C$6-$C$5)/7) -> 62
A12: Remaining days | C12: =MOD($C$6-$C$5,7) -> 0
A13: Approximate months (30.4375-day avg) | C13: =($C$6-$C$5)/30.4375 -> 14.258727
A14: Weekdays / weekend days in span | C14: 311 / 124 | D14: Calendar composition to 2026-08-19 (computed; recompute if as-of changes). Not proof of days worked.
A16: THREE ERAS, THREE KINDS OF EVIDENCE
A17: Era | B17: Period | C17: Business activity | D17: Hours | E17: Evidence tier
A18: 1 — Strategy R&D (Woven Basket) | B18: 2025-06-11 → 2026-05-17 | C18: R&D, strategy development, IP development: credit-collar precursor → $2k/month income system → seven-layer Woven Basket v1-5 (proprietary IP) | D18: Not recoverable | E18: Reconstructed from recovered conversation records; Medium/Low confidence
A19: 2 — Platform foundation | B19: 2026-05-15 → 2026-06-01 | C19: System development begins: first Trezo folder (May 15, 15:43:15), environment and design work predating version control. Note: overlaps Era 1 — Woven Basket v1-5 (May 17) was finalized as platform work began. | D19: Not recoverable | E19: Folder timestamp (high); period contents user-recalled
A20: 3 — Platform build (Trezo) | B20: 2026-06-01 → present | C20: System development, revision, documentation: 198 commits, 22 agents, 3 books, ops hardening, profit-protection system | D20: ="≥ "&TEXT('Work Log (Trezo)'!F88,"0.0")&" h (floor)" -> ≥ 218.3 h (floor) | E20: Git commit history (high); hours are a floor — see Method
A22: KEY CONCLUSION
A23: The available record supports a continuous development arc from at least June 11, 2025 through the present: strategy R&D culminating in Woven Basket v1-5, flowing directly into the Trezo platform that implements it. Active-work hours are defensible only for Era 3 (git-evidenced floor, currently 218.3 h plus manual additions). Eras 1–2 are spans with substantiated milestones, not hour claims — original chat or file-version timestamps can be added later to upgrade them.

Sheet Unified Timeline
A1: UNIFIED DEVELOPMENT TIMELINE
A2: Every substantiated milestone across both records, in order. Fill color = evidence tier.
A4: Date | B4: Era | C4: Phase | D4: What happened | E4: Evidence / source | F4: Confidence
A5: 2025-06-11 | B5: 1 | C5: Foundation | D5: Nokia recurring-premium / portfolio-protection precursor work begins. | E5: Recovered ChatGPT record (turn 6caf0a78…) | F5: Medium
A6: 2025-06-16 | B6: 1 | C6: Foundation | D6: Credit-collar structure: shares, short calls, long puts, roll/management logic. | E6: Recovered ChatGPT record (turn 6caf0a78…) | F6: Medium
A7: 2025-09-24 | B7: 1 | C7: Income system | D7: Stock/options system targeting ~$2,000/month — ancestor of the income architecture. | E7: Recovered ChatGPT record (turn 6caf0a78…) | F7: Medium
A8: 2026-01→02 | B8: 1 | C8: Integration | D8: Extended work and several documents recalled; artifacts not recovered. | E8: User recollection only | F8: Low
A9: 2026-03 | B9: 1 | C9: Integration | D9: Precursor concepts leading into Woven Basket reported in earlier review. | E9: Assistant statement (turn b21e376d…) | F9: Low
A10: 2026-05-13 | B10: 1 | C10: Formalization | D10: The Woven Basket Investment Strategy named: seven interconnected layers, cross-layer protection, cash-flow waterfall. | E10: Recovered ChatGPT record (turns b21e376d…, 4d170423…) | F10: Medium
A11: 2026-05-15 | B11: 2 | C11: Foundation | D11: First Trezo folder created, 3:43:15 PM — platform work begins. | E11: Folder creation timestamp | F11: High
A12: 2026-05-17 | B12: 1 | C12: Culmination | D12: Woven Basket v1-5 — architecture identified as proprietary IP. Strategy finalized as platform work began. | E12: Recovered ChatGPT record (turn 4d170423…) | F12: Medium
A13: 2026-06-01 | B13: 3 | C13: Baseline | D13: First commit: paper page recovered, capital pressure shipped. Version control begins. | E13: Git commit | F13: High
A14: 2026-06-12 | B14: 3 | C14: Hardening | D14: Marathon audit: 32 fixes — crypto exits, Wheel universe, position trimming. | E14: Git commits | F14: High
A15: 2026-06-13 | B15: 3 | C15: Crypto lane | D15: Crypto Part 1: classification fixed, HODL accumulate-and-hold added. | E15: Git commits (10) | F15: High
A16: 2026-07-02 | B16: 3 | C16: Realism | D16: ATR-capped realistic targets; crypto revival (dead-SCALP bug, live volume). | E16: Git commits (12) | F16: High
... A24: 2026-08-19 | B24: 3 | C24: Turnaround | D24: Profit ladder retuned from 30-day evidence; single-engine enforcement; DCA bounce gate; ~$1,900 locked in first 15 minutes; 5k book recrosses $5,000. | E24: Git commits (11) + broker screenshots | F24: High
A26: Green = substantiated (recovered record, timestamp, or git). Gold = inferred / user-recalled — kept, labeled, and excluded from any hour total.

Sheet Work Log (Trezo)
A1: ERA 3 WORK LOG — GIT-DERIVED + MANUAL
A2: Rows marked git regenerate from commit history (tools/worklog.py). Yellow manual rows are yours.
A4: Date | B4: Month | C4: Commits | D4: First | E4: Last | F4: Hours | G4: Source | H4: What shipped / notes
A5: 46174 | B5: =TEXT(A5,"YYYY-MM") -> 2026-06 | C5: 1 | D5: 18:45 | E5: 18:45 | F5: 1 | G5: git | H5: Trezo baseline 2026-06-01 - paper page recovered, capital pressure shipped
A6: 46176 | B6: =TEXT(A6,"YYYY-MM") -> 2026-06 | C6: 1 | D6: 20:12 | E6: 20:12 | F6: 1 | G6: git | H6: Trezo snapshot 2026-06-03 - all green: 22 agents, sliding-scale giveback, OpsWatchdog, auto-reconcile
A7: 46177 | B7: =TEXT(A7,"YYYY-MM") -> 2026-06 | C7: 1 | D7: 11:54 | E7: 11:54 | F7: 1 | G7: git | H7: Trezo snapshot 2026-06-04 - all green: 22 agents, sliding-scale giveback, OpsWatchdog, auto-reconcile
A8: 46185 | B8: =TEXT(A8,"YYYY-MM") -> 2026-06 | C8: 3 | D8: 02:29 | E8: 22:07 | F8: 19.63 | G8: git | H8: 2026-06-11/12 marathon audit: 32 fixes - crypto exits, Wheel full-market universe, trim_positions
A9: 46186 | B9: =TEXT(A9,"YYYY-MM") -> 2026-06 | C9: 10 | D9: 04:13 | E9: 18:30 | F9: 14.28 | G9: git | H9: Crypto Part 1: fix crypto classification (ISO coins -> modeled engine), add HODL accumulate-and-hold
A10: 46189 | B10: =TEXT(A10,"YYYY-MM") -> 2026-06 | C10: 1 | D10: 17:47 | E10: 17:47 | F10: 1 | G10: git | H10: 6/16 bug-fix + self-healing integrity sweep
A11: 46190 | B11: =TEXT(A11,"YYYY-MM") -> 2026-06 | C11: 2 | D11: 02:08 | E11: 08:25 | F11: 6.28 | G11: git | H11: 6/16 learning loop: outcome-weighted strategy selection + macro fall-through
A12: 46192 | B12: =TEXT(A12,"YYYY-MM") -> 2026-06 | C12: 9 | D12: 05:17 | E12: 17:10 | F12: 11.88 | G12: git | H12: Paper page: positions/trades up top; account-size testing to Strategy Lab
A13: 46196 | B13: =TEXT(A13,"YYYY-MM") -> 2026-06 | C13: 2 | D13: 13:47 | E13: 14:18 | F13: 1 | G13: git | H13: Trading: integrity flags - classify positions Live/Modeled/Unconfirmed vs Alpaca
A14: 46199 | B14: =TEXT(A14,"YYYY-MM") -> 2026-06 | C14: 3 | D14: 18:32 | E14: 19:22 | F14: 1 | G14: git | H14: Agents: route crypto + options exits through the shared capability library
A15: 46202 | B15: =TEXT(A15,"YYYY-MM") -> 2026-06 | C15: 3 | D15: 13:55 | E15: 16:18 | F15: 2.38 | G15: git | H15: Trading page: show why each position is held + its path to profit
A16: 46204 | B16: =TEXT(A16,"YYYY-MM") -> 2026-07 | C16: 2 | D16: 22:25 | E16: 22:39 | F16: 1 | G16: git | H16: Visibility pack: activity log wired into vetoes, approvals, pocket skips, submits, broker rejects
... A43: 46253 | B43: =TEXT(A43,"YYYY-MM") -> 2026-08 | C43: 11 | D43: 00:03 | E43: 23:10 | F43: 23.12 | G43: git | H43: Profit ladder retuned + rival-engine cleanup + DCA bounce gate + work log tooling
A45: MANUAL ENTRIES — pre-repo days, research, SQL, server ops, calls
A46: 46158 | B46: =TEXT(A46,"YYYY-MM") -> 2026-05 | D46: 09:00 | E46: 13:30 | F46: 4.5 | G46: example | H46: EXAMPLE ROW — platform planning, no commits. Delete or overwrite.
B47: =IF(A47="","",TEXT(A47,"YYYY-MM")) | G47: manual
B48: =IF(A48="","",TEXT(A48,"YYYY-MM")) | G48: manual
B49: =IF(A49="","",TEXT(A49,"YYYY-MM")) | G49: manual
B50: =IF(A50="","",TEXT(A50,"YYYY-MM")) | G50: manual
B51: =IF(A51="","",TEXT(A51,"YYYY-MM")) | G51: manual
B52: =IF(A52="","",TEXT(A52,"YYYY-MM")) | G52: manual
B53: =IF(A53="","",TEXT(A53,"YYYY-MM")) | G53: manual
B54: =IF(A54="","",TEXT(A54,"YYYY-MM")) | G54: manual
B55: =IF(A55="","",TEXT(A55,"YYYY-MM")) | G55: manual
B56: =IF(A56="","",TEXT(A56,"YYYY-MM")) | G56: manual
B57: =IF(A57="","",TEXT(A57,"YYYY-MM")) | G57: manual
B58: =IF(A58="","",TEXT(A58,"YYYY-MM")) | G58: manual
... B86: =IF(A86="","",TEXT(A86,"YYYY-MM")) | G86: manual
A88: TOTAL RECORDED HOURS (Era 3) | F88: =SUMIF($G$5:$G$86,"git",$F$5:$F$86)+SUMIF($G$5:$G$86,"manual",$F$5:$F$86) -> 218.3

Sheet Monthly (Trezo)
A1: ERA 3 MONTHLY SUBTOTALS
A3: Month | B3: Days recorded | C3: Commits | D3: Hours | E3: % of hours
A4: 2026-05 | B4: =COUNTIFS('Work Log (Trezo)'!$B$5:$B$86,$A4,'Work Log (Trezo)'!$G$5:$G$86,"git")+COUNTIFS('Work Log (Trezo)'!$B$5:$B$86,$A4,'Work Log (Trezo)'!$G$5:$G$86,"manual") -> 0 | C4: =SUMIFS('Work Log (Trezo)'!$C$5:$C$86,'Work Log (Trezo)'!$B$5:$B$86,$A4,'Work Log (Trezo)'!$G$5:$G$86,"git") -> 0 | D4: =SUMIFS('Work Log (Trezo)'!$F$5:$F$86,'Work Log (Trezo)'!$B$5:$B$86,$A4,'Work Log (Trezo)'!$G$5:$G$86,"git")+SUMIFS('Work Log (Trezo)'!$F$5:$F$86,'Work Log (Trezo)'!$B$5:$B$86,$A4,'Work Log (Trezo)'!$G$5:$G$86,"manual") -> 0 | E4: =IFERROR($D4/$D$8,0) -> 0
A5: 2026-06 | B5: =COUNTIFS('Work Log (Trezo)'!$B$5:$B$86,$A5,'Work Log (Trezo)'!$G$5:$G$86,"git")+COUNTIFS('Work Log (Trezo)'!$B$5:$B$86,$A5,'Work Log (Trezo)'!$G$5:$G$86,"manual") -> 11 | C5: =SUMIFS('Work Log (Trezo)'!$C$5:$C$86,'Work Log (Trezo)'!$B$5:$B$86,$A5,'Work Log (Trezo)'!$G$5:$G$86,"git") -> 36 | D5: =SUMIFS('Work Log (Trezo)'!$F$5:$F$86,'Work Log (Trezo)'!$B$5:$B$86,$A5,'Work Log (Trezo)'!$G$5:$G$86,"git")+SUMIFS('Work Log (Trezo)'!$F$5:$F$86,'Work Log (Trezo)'!$B$5:$B$86,$A5,'Work Log (Trezo)'!$G$5:$G$86,"manual") -> 60.45 | E5: =IFERROR($D5/$D$8,0) -> 0.27691251
A6: 2026-07 | B6: =COUNTIFS('Work Log (Trezo)'!$B$5:$B$86,$A6,'Work Log (Trezo)'!$G$5:$G$86,"git")+COUNTIFS('Work Log (Trezo)'!$B$5:$B$86,$A6,'Work Log (Trezo)'!$G$5:$G$86,"manual") -> 17 | C6: =SUMIFS('Work Log (Trezo)'!$C$5:$C$86,'Work Log (Trezo)'!$B$5:$B$86,$A6,'Work Log (Trezo)'!$G$5:$G$86,"git") -> 80 | D6: =SUMIFS('Work Log (Trezo)'!$F$5:$F$86,'Work Log (Trezo)'!$B$5:$B$86,$A6,'Work Log (Trezo)'!$G$5:$G$86,"git")+SUMIFS('Work Log (Trezo)'!$F$5:$F$86,'Work Log (Trezo)'!$B$5:$B$86,$A6,'Work Log (Trezo)'!$G$5:$G$86,"manual") -> 72 | E6: =IFERROR($D6/$D$8,0) -> 0.32982135
A7: 2026-08 | B7: =COUNTIFS('Work Log (Trezo)'!$B$5:$B$86,$A7,'Work Log (Trezo)'!$G$5:$G$86,"git")+COUNTIFS('Work Log (Trezo)'!$B$5:$B$86,$A7,'Work Log (Trezo)'!$G$5:$G$86,"manual") -> 11 | C7: =SUMIFS('Work Log (Trezo)'!$C$5:$C$86,'Work Log (Trezo)'!$B$5:$B$86,$A7,'Work Log (Trezo)'!$G$5:$G$86,"git") -> 82 | D7: =SUMIFS('Work Log (Trezo)'!$F$5:$F$86,'Work Log (Trezo)'!$B$5:$B$86,$A7,'Work Log (Trezo)'!$G$5:$G$86,"git")+SUMIFS('Work Log (Trezo)'!$F$5:$F$86,'Work Log (Trezo)'!$B$5:$B$86,$A7,'Work Log (Trezo)'!$G$5:$G$86,"manual") -> 85.85 | E7: =IFERROR($D7/$D$8,0) -> 0.39326615
A8: TOTAL | B8: =SUM(B4:B7) -> 39 | C8: =SUM(C4:C7) -> 198 | D8: =SUM(D4:D7) -> 218.3 | E8: =SUM(E4:E7) -> 1
A10: 2026-05 = 0 until pre-repo work is added as manual rows on the Work Log tab.

Sheet WB Timeline
A1: ERA 1 — WOVEN BASKET DEVELOPMENT TIMELINE (imported)
A2: Imported unchanged from Woven_Basket_Strategy_Development_Timeline.xlsx. Blank durations mean the source does not support an exact interval — hours are NOT RECOVERABLE, not zero.
A4: Start | B4: End | C4: Days | D4: Document / version | E4: Work performed | F4: Evidence | G4: Confidence | H4: Classification
A5: 2025-06-11 | B5: 2025-06-16 | C5: 5 | D5: Nokia recurring-premium / protection precursor | E5: Recurring-premium and portfolio-protection concepts; by June 16: shares, short calls, long puts, roll/management logic. | F5: ChatGPT task record; turn 6caf0a78… | G5: Medium | H5: VERIFIED milestone; hours unknown
A6: 2025-09-24 | B6: 2025-09-24 | C6: 0 | D6: $2,000/month stock-options system precursor | E6: Stock/options system targeting ~$2,000/month — ancestor of the income architecture. | F6: ChatGPT task record; turn 6caf0a78… | G6: Medium | H6: VERIFIED milestone; hours unknown
A7: 2026-01-01 | B7: 2026-02-28 | C7: 58 | D7: Unrecovered January–February precursor documents | E7: Extended work and several documents recalled; exact dates, versions and durations not recovered. | F7: User recollection; no artifact recovered | G7: Low | H7: INFERRED / USER-RECALLED
A8: 2026-03-01 | B8: 2026-03-31 | C8: 30 | D8: Unnamed Woven Basket precursor concepts | E8: March evidence of concepts leading into Woven Basket reported; conversation/date not preserved. | F8: Assistant statement; turn b21e376d… | G8: Low | H8: INFERRED milestone; hours unknown
A9: 2026-05-13 | B9: 2026-05-13 | C9: 0 | D9: The Woven Basket Investment Strategy (earliest named; v1-2 or earlier) | E9: Named strategy: seven interconnected layers, cross-layer protection logic, cash-flow waterfall. | F9: ChatGPT task record; turns b21e376d…, 4d170423… | G9: Medium | H9: VERIFIED milestone; hours unknown
A10: 2026-05-17 | B10: 2026-05-17 | C10: 0 | D10: Woven Basket Strategy v1-5 (latest recovered) | E10: Refined architecture identified as proprietary IP. Culmination point of the reconstruction; finality not independently proven. | F10: ChatGPT task record; turns 4d170423…, b21e376d… | G10: Medium | H10: VERIFIED milestone; hours unknown
A12: Evidence register (E-01…E-05), calculation rules and audit notes remain in the companion file Woven_Basket_Strategy_Development_Timeline.xlsx, which stays the source of record for Era 1.

Sheet Method
A1: METHOD, EVIDENCE TIERS & LIMITS
A3: Purpose
A4: A single good-faith business record of the development of the Woven Basket strategy and the Trezo platform that implements it, suitable for personal accountability records. It shows continuous work from June 2025 to the present while never claiming more precision than the evidence supports.
A8: Evidence tiers
A9: HIGH: git commit history and filesystem timestamps — independently verifiable. MEDIUM: recovered conversation records naming dates and artifacts. LOW: user recollection without a recovered artifact — kept for context, never counted in hours.
A13: Hours policy
A14: Hours appear ONLY where evidence supports them. Era 3's total is a floor derived from commit-day spans (tools/worklog.py in the repo regenerates it). Eras 1–2 say 'not recoverable' rather than reporting a false zero or an invented estimate. Original chat timestamps or document version histories, if recovered later, can be added as manual rows to upgrade the record.
A18: Continuity
A19: The two records overlap by design: the first Trezo folder (2026-05-15 15:43:15) predates Woven Basket v1-5 (2026-05-17). The strategy was being finalized as its implementation began — Era 1 flows into Era 3 without a gap.
A23: Classification of activity
A24: Era 1: research & development, strategy development, IP development. Era 2: system development (foundation). Era 3: system development, revision, documentation — per-day detail on the Work Log tab.
A28: If this is used for business records
A29: This workbook provides dates, evidence and hour floors. Whether any of it is claimable as business time or expense is a question for a CPA.
